{
  "version": 3,
  "createdAt": "2026-05-28T12:42:34.637Z",
  "workspaces": [
    {
      "name": "enjiri-center-ministries",
      "title": "Enjiri Center Ministries International",
      "basePath": "/studio",
      "projectId": "shcw5txc",
      "dataset": "production",
      "icon": "<svg xmlns=\"http://www.w3.org/2000/svg\" viewBox=\"0 0 32 32\"><rect width=\"32\" height=\"32\" rx=\"2\" fill=\"#8f57ef\"></rect><text x=\"50%\" y=\"50%\" text-anchor=\"middle\" alignment-baseline=\"middle\" fill=\"hsla(262, 83%, 24%, 1)\" style=\"font-family:Inter, -apple-system, BlinkMacSystemFont, &quot;Segoe UI&quot;, Roboto, &quot;Helvetica Neue&quot;, &quot;Liberation Sans&quot;, Helvetica, Arial, system-ui, sans-serif;font-weight:500;font-size:13px;transform:translateY(1px)\">EC</text></svg>",
      "mediaLibrary": {
        "enabled": false,
        "__internal": {}
      },
      "schema": "3a5ae64f.create-schema.json",
      "tools": "ba47da56.create-tools.json"
    }
  ],
  "studioVersion": "5.11.0"
}